givemehelp/__init__.py
givemehelp/main.py
givemehelp-0.75.dist-info/LICENSE
givemehelp-0.75.dist-info/METADATA
givemehelp-0.75.dist-info/WHEEL
givemehelp-0.75.dist-info/entry_points.txt
givemehelp-0.75.dist-info/top_level.txt
givemehelp-0.75.dist-info/RECORD
